{"cameraMode":{"drawMode":0,"name":"Shaded","section":"Shading Mode"},"sceneLighting":true,"audioPlay":false,"sceneViewState":{"showFog":true,"showMaterialUpdate":false,"showSkybox":true,"showFlares":true,"showImageEffects":true,"showParticleSystems":true},"in2DMode":false,"pivot":{"x":7.797354221343994,"y":-0.1355438232421875,"z":22.38123321533203},"rotation":{"x":0.6963828802108765,"y":0.007534986361861229,"z":-0.007312310393899679,"w":0.7175934314727783},"size":19.11988639831543,"orthographic":false}